reading163/__init__.py
reading163-0.0.4.dist-info/LICENSE
reading163-0.0.4.dist-info/METADATA
reading163-0.0.4.dist-info/WHEEL
reading163-0.0.4.dist-info/top_level.txt
reading163-0.0.4.dist-info/RECORD
