Metadata-Version: 2.1
Name: reading163
Version: 0.0.4
Summary: make it easy to use reading163
Home-page: https://gitee.com/ZeroSeeker/reading163
Author: ZeroSeeker
Author-email: zeroseeker@foxmail.com
License: UNKNOWN
Platform: UNKNOWN
Classifier: Programming Language :: Python :: 3
Classifier: License :: OSI Approved :: MIT License
Classifier: Operating System :: OS Independent
License-File: LICENSE
Requires-Dist: envx (==0.0.5)
Requires-Dist: requests (==2.27.1)
